pip_fc/__init__.py
pip_fc/__main__.py
pip_fc/core.py
pip_fc-0.1.12.dist-info/licenses/LICENSE
pip_fc-0.1.12.dist-info/METADATA
pip_fc-0.1.12.dist-info/WHEEL
pip_fc-0.1.12.dist-info/entry_points.txt
pip_fc-0.1.12.dist-info/top_level.txt
pip_fc-0.1.12.dist-info/RECORD
