Metadata-Version: 2.1
Name: pip-fc
Version: 0.1.12
Summary: 一款轻量级的 Python 工具，用于高效测试多个镜像源的连接速度，帮助用户选择最优的镜像源以提高包管理效率。
Home-page: https://github.com/harmonsir/pip-fc
Author: HarmonSir
Author-email: git@pylab.me
License: UNKNOWN
Keywords: mlc-mirror mirror speed pip
Platform: UNKNOWN
Classifier: Programming Language :: Python :: 2.7
Classifier: Programming Language :: Python :: 3
Classifier: License :: OSI Approved :: MIT License
Classifier: Operating System :: OS Independent
Requires-Python: >=2.7, <4
